tamilscraper.py
tamilscraper-0.0.1.dist-info/LICENSE
tamilscraper-0.0.1.dist-info/METADATA
tamilscraper-0.0.1.dist-info/WHEEL
tamilscraper-0.0.1.dist-info/top_level.txt
tamilscraper-0.0.1.dist-info/RECORD
