Metadata-Version: 2.1
Name: tamilscraper
Version: 0.0.1
Summary: Web Scraping tool for Tamil Language
Author: Gokul S
Classifier: Programming Language :: Python :: 3
Classifier: License :: OSI Approved :: MIT License
Classifier: Operating System :: OS Independent
Requires-Python: >=3.8
License-File: LICENSE
